LICENSE.txt
MANIFEST.in
README.md
setup.py
EIAOpenData/__init__.py
EIAOpenData/eia_opendata.py
EIAOpenData.egg-info/PKG-INFO
EIAOpenData.egg-info/SOURCES.txt
EIAOpenData.egg-info/dependency_links.txt
EIAOpenData.egg-info/requires.txt
EIAOpenData.egg-info/top_level.txt