Metadata-Version: 2.1
Name: EIAOpenData
Version: 0.1.1
Summary: EIAOpenData is a Python package that provides easy access to various energy-related data obtained from the Energy Information Administration (EIA) API.
Home-page: https://github.com/urazakgul/EIAOpenData
Author: Uraz Akgül
Author-email: urazdev@gmail.com
License: MIT
Classifier: Programming Language :: Python :: 3
Classifier: License :: OSI Approved :: MIT License
Classifier: Operating System :: OS Independent
Requires-Python: >=3.8
License-File: LICENSE.txt
